xmdim/__init__.py
xmdim/dim.py
xmdim-0.0.1.dist-info/METADATA
xmdim-0.0.1.dist-info/WHEEL
xmdim-0.0.1.dist-info/licenses/LICENSE
xmdim-0.0.1.dist-info/RECORD
